{
  "project_info": {
    "project_number": "422515360756",
    "project_id": "haca-95e97",
    "storage_bucket": "haca-95e97.firebasestorage.app"
  },
  "client": [
    {
      "client_info": {
        "mobilesdk_app_id": "1:422515360756:android:3080815e430006665c2fa1",
        "android_client_info": {
          "package_name": "com.example.haca_review_main"
        }
      },
      "oauth_client": [],
      "api_key": [
        {
          "current_key": "AIzaSyBLWJcwcyEqBo--UXT4YSoKhX_ilS0Ga58"
        }
      ],
      "services": {
        "appinvite_service": {
          "other_platform_oauth_client": []
        }
      }
    }
  ],
  "configuration_version": "1"
}